fast_tavern/__init__.py
fast_tavern/core/__init__.py
fast_tavern/core/convert.py
fast_tavern/core/types.py
fast_tavern/core/channels/__init__.py
fast_tavern/core/channels/detect.py
fast_tavern/core/channels/gemini.py
fast_tavern/core/channels/openai.py
fast_tavern/core/channels/tagged.py
fast_tavern/core/channels/text.py
fast_tavern/core/modules/__init__.py
fast_tavern/core/modules/assemble/__init__.py
fast_tavern/core/modules/assemble/assemble_tagged_prompt_list.py
fast_tavern/core/modules/build/__init__.py
fast_tavern/core/modules/build/build_prompt.py
fast_tavern/core/modules/history/__init__.py
fast_tavern/core/modules/history/factories.py
fast_tavern/core/modules/history/guards.py
fast_tavern/core/modules/inputs/__init__.py
fast_tavern/core/modules/inputs/normalize_regexes.py
fast_tavern/core/modules/inputs/normalize_worldbooks.py
fast_tavern/core/modules/macro/__init__.py
fast_tavern/core/modules/macro/replace_macros.py
fast_tavern/core/modules/pipeline/__init__.py
fast_tavern/core/modules/pipeline/compile_tagged_stages.py
fast_tavern/core/modules/pipeline/process_content_stages.py
fast_tavern/core/modules/regex/__init__.py
fast_tavern/core/modules/regex/apply_regex.py
fast_tavern/core/modules/regex/merge_regex_rules.py
fast_tavern/core/modules/variables/__init__.py
fast_tavern/core/modules/variables/variable_context.py
fast_tavern/core/modules/worldbook/__init__.py
fast_tavern/core/modules/worldbook/get_active_entries.py
fast_tavern-0.1.4.dist-info/METADATA
fast_tavern-0.1.4.dist-info/WHEEL
fast_tavern-0.1.4.dist-info/RECORD
