Metadata-Version: 2.4
Name: fast-tavern
Version: 0.1.4
Summary: A framework-agnostic prompt engine: preset + worldbook + character + regex + macros -> compiled messages.
License: MIT
Keywords: macro,prompt,regex,sillytavern,worldbook
Requires-Python: >=3.10
Provides-Extra: dev
Requires-Dist: pytest>=7.0; extra == 'dev'
